matrix_count-0.1.6.dist-info/METADATA
matrix_count-0.1.6.dist-info/RECORD
matrix_count-0.1.6.dist-info/WHEEL
matrix_count-0.1.6.dist-info/licenses/LICENSE
matrix_count/__init__.py
matrix_count/_util.py
matrix_count/sample_core.pyi
matrix_count/_version.pyi
matrix_count/_input_output.py
matrix_count/count.py
matrix_count/sample.py
matrix_count/_version.py
matrix_count/py.typed
matrix_count/sample_binary_core.pyi
matrix_count/sample_core.cpython-311-i386-linux-gnu.so
matrix_count/sample_binary_core.cpython-311-i386-linux-gnu.so
matrix_count/estimate.py
